{
  "$schema": "https://developer.microsoft.com/json-schemas/fabric/item/report/definition/visualContainer/1.0.0/schema.json",
  "name": "366c710008c6a093e306",
  "position": {
    "x": 960.48,
    "y": 436.32,
    "z": 38000,
    "width": 165.6,
    "height": 133.92000000000002,
    "tabOrder": 38000
  },
  "visual": {
    "visualType": "pieChart",
    "query": {
      "queryState": {
        "Y": {
          "projections": [
            {
              "field": {
                "Measure": {
                  "Expression": {
                    "SourceRef": {
                      "Entity": "Measure"
                    }
                  },
                  "Property": "Total Collection"
                }
              },
              "queryRef": "Measure.Total Collection"
            },
            {
              "field": {
                "Measure": {
                  "Expression": {
                    "SourceRef": {
                      "Entity": "Measure"
                    }
                  },
                  "Property": "OS Balance"
                }
              },
              "queryRef": "Measure.OS Balance",
              "nativeQueryRef": "Outstanding",
              "displayName": "Outstanding"
            }
          ]
        }
      },
      "sortDefinition": {
        "sort": [
          {
            "field": {
              "Measure": {
                "Expression": {
                  "SourceRef": {
                    "Entity": "Measure"
                  }
                },
                "Property": "Total Collection"
              }
            },
            "direction": "Descending"
          }
        ],
        "isDefaultSort": true
      }
    },
    "objects": {
      "labels": [
        {
          "properties": {
            "show": {
              "expr": {
                "Literal": {
                  "Value": "true"
                }
              }
            },
            "labelStyle": {
              "expr": {
                "Literal": {
                  "Value": "'Category, percent of total'"
                }
              }
            },
            "position": {
              "expr": {
                "Literal": {
                  "Value": "'outside'"
                }
              }
            },
            "fontSize": {
              "expr": {
                "Literal": {
                  "Value": "8D"
                }
              }
            },
            "labelDisplayUnits": {
              "expr": {
                "Literal": {
                  "Value": "1000000D"
                }
              }
            }
          }
        }
      ],
      "legend": [
        {
          "properties": {
            "show": {
              "expr": {
                "Literal": {
                  "Value": "false"
                }
              }
            }
          }
        }
      ],
      "dataPoint": [
        {
          "properties": {
            "fill": {
              "solid": {
                "color": {
                  "expr": {
                    "Literal": {
                      "Value": "'#19E41C'"
                    }
                  }
                }
              }
            }
          },
          "selector": {
            "metadata": "Measure.Total Collection"
          }
        }
      ]
    },
    "visualContainerObjects": {
      "title": [
        {
          "properties": {
            "show": {
              "expr": {
                "Literal": {
                  "Value": "false"
                }
              }
            }
          }
        }
      ],
      "background": [
        {
          "properties": {
            "show": {
              "expr": {
                "Literal": {
                  "Value": "false"
                }
              }
            }
          }
        }
      ]
    },
    "drillFilterOtherVisuals": true
  }
}