{
  "$schema": "https://developer.microsoft.com/json-schemas/fabric/item/report/definition/visualContainer/1.0.0/schema.json",
  "name": "2a31d6a024fd179e9e55",
  "position": {
    "x": 387.93057409879839,
    "y": 6.8357810413885174,
    "z": 15000,
    "width": 68.357810413885176,
    "height": 75.19359145527369,
    "tabOrder": 15000
  },
  "visual": {
    "visualType": "image",
    "objects": {
      "general": [
        {
          "properties": {
            "imageUrl": {
              "expr": {
                "ResourcePackageItem": {
                  "PackageName": "RegisteredResources",
                  "PackageType": 1,
                  "ItemName": "pngegg9249213018820028.png"
                }
              }
            }
          }
        }
      ]
    },
    "drillFilterOtherVisuals": true
  }
}